generalizedtrees/__init__.py
generalizedtrees/constraints.py
generalizedtrees/features.py
generalizedtrees/generate.py
generalizedtrees/givens.py
generalizedtrees/grow.py
generalizedtrees/learn.py
generalizedtrees/leaves.py
generalizedtrees/node.py
generalizedtrees/predict.py
generalizedtrees/queues.py
generalizedtrees/recipes.py
generalizedtrees/scores.py
generalizedtrees/split.py
generalizedtrees/stop.py
generalizedtrees/tree.py
generalizedtrees/util.py
generalizedtrees/vis/__init__.py
generalizedtrees/vis/decision_tree.js
generalizedtrees/vis/models.py
generalizedtrees/vis/nb_template.html
generalizedtrees/vis/notebook.py
generalizedtrees/vis/template.html
generalizedtrees/vis/util.py
generalizedtrees/vis/vis.py
generalizedtrees-1.2.0.dist-info/LICENSE
generalizedtrees-1.2.0.dist-info/METADATA
generalizedtrees-1.2.0.dist-info/WHEEL
generalizedtrees-1.2.0.dist-info/top_level.txt
generalizedtrees-1.2.0.dist-info/RECORD
