Metadata-Version: 2.1
Name: generalizedtrees
Version: 1.2.0
Summary: Library for tree models: decision trees, model trees, mimic models, etc.
Home-page: https://github.com/Craven-Biostat-Lab/generalizedtrees
Author: Yuriy Sverchkov
Author-email: yuriy.sverchkov@wisc.edu
License: BSD (3 clause)
Keywords: machine learning decision trees model
Platform: UNKNOWN
Classifier: Programming Language :: Python :: 3
Classifier: License :: OSI Approved :: BSD License
Classifier: Development Status :: 2 - Pre-Alpha
Classifier: Operating System :: OS Independent
Classifier: Topic :: Scientific/Engineering
Requires-Python: >=3.8
Requires-Dist: scikit-learn (>=0.23.2)
Requires-Dist: numpy (>=1.19.1)
Requires-Dist: scipy (>=1.5.2)
Requires-Dist: pandas (>=1.1.0)
